README.md
setup.py
cc_py_commons/__init__.py
cc_py_commons/geolocate.py
cc_py_commons.egg-info/PKG-INFO
cc_py_commons.egg-info/SOURCES.txt
cc_py_commons.egg-info/dependency_links.txt
cc_py_commons.egg-info/requires.txt
cc_py_commons.egg-info/top_level.txt
cc_py_commons/bids/__init__.py
cc_py_commons/bids/bid.py
cc_py_commons/bids/bid_history.py
cc_py_commons/bids/bid_history_schema.py
cc_py_commons/bids/bid_schema.py
cc_py_commons/carriers/__init__.py
cc_py_commons/carriers/account_carrier_map.py
cc_py_commons/carriers/account_carrier_map_schema.py
cc_py_commons/carriers/carrier.py
cc_py_commons/carriers/carrier_schema.py
cc_py_commons/carriers/contact.py
cc_py_commons/carriers/contact_schema.py
cc_py_commons/config/__init__.py
cc_py_commons/config/c4_account_settings.py
cc_py_commons/config/env.py
cc_py_commons/config/mcleod_load_fields.py
cc_py_commons/config/pc_miler_config.py
cc_py_commons/config/web_socket_action.py
cc_py_commons/db/__init__.py
cc_py_commons/db/connection.py
cc_py_commons/lanes/__init__.py
cc_py_commons/lanes/carrier_lane.py
cc_py_commons/lanes/carrier_lane_schema.py
cc_py_commons/lanes/lane.py
cc_py_commons/lanes/lane_schema.py
cc_py_commons/loads/__init__.py
cc_py_commons/loads/equipment.py
cc_py_commons/loads/equipment_schema.py
cc_py_commons/loads/equipment_types.py
cc_py_commons/loads/freighthub_contact.py
cc_py_commons/loads/freighthub_contact_schema.py
cc_py_commons/loads/load.py
cc_py_commons/loads/load_schema.py
cc_py_commons/loads/load_status.py
cc_py_commons/loads/location.py
cc_py_commons/loads/location_schema.py
cc_py_commons/loads/map_load_response.py
cc_py_commons/projects/__init__.py
cc_py_commons/projects/project.py
cc_py_commons/projects/project_schema.py
cc_py_commons/quotes/__init__.py
cc_py_commons/quotes/quote.py
cc_py_commons/quotes/quote_schema.py
cc_py_commons/quotes/quote_status.py
cc_py_commons/rfp/__init__.py
cc_py_commons/rfp/create_table.py
cc_py_commons/rfp/rfp_status.py
cc_py_commons/rfp/truck_lane_search_mapper.py
cc_py_commons/schemas/__init__.py
cc_py_commons/schemas/camel_case_schema.py
cc_py_commons/services/__init__.py
cc_py_commons/services/analytics/__init__.py
