Metadata-Version: 2.4
Name: cc_py_commons
Version: 0.5.65
Summary: Common code for microservices
Home-page: https://github.com/Cargo-Chief/py-commons
Author: CargoChief
Author-email: engineering@cargochief.com
Requires-Dist: requests
Requires-Dist: googlemaps
Requires-Dist: marshmallow
Requires-Dist: boto3
Requires-Dist: inflection
Requires-Dist: pytz
Dynamic: author
Dynamic: author-email
Dynamic: home-page
Dynamic: requires-dist
Dynamic: summary
